dotboy/__init__.py
dotboy/__main__.py
dotboy/config.py
dotboy/dotboy.py
dotboy/path_info.py
dotboy-0.3.1.dist-info/LICENSE
dotboy-0.3.1.dist-info/METADATA
dotboy-0.3.1.dist-info/WHEEL
dotboy-0.3.1.dist-info/top_level.txt
dotboy-0.3.1.dist-info/RECORD
