Metadata-Version: 2.1
Name: dotboy
Version: 0.3.1
Summary: A Python script to help with dot file management
Home-page: https://gitlab.com/bwbuhse/dotboy
Author: Ben Buhse
Author-email: ben@buhses.com
License: UNKNOWN
Platform: UNKNOWN
Classifier: Programming Language :: Python :: 3
Classifier: License :: OSI Approved :: MIT License
Classifier: Operating System :: OS Independent
Requires-Python: >=3.8
Requires-Dist: GitPython
